Metadata-Version: 2.1
Name: cellxgene-gateway
Version: 0.4.0
Summary: Cellxgene Gateway
Home-page: http://github.com/Novartis/cellxgene-gateway
Author: Niket Patel, Yohann Potier, Alok Saldanha
Author-email: alok.saldanha@novartis.com
License: MIT
Keywords: visualization,genomics
Classifier: Topic :: Scientific/Engineering :: Visualization
Requires-Python: >=3.6
License-File: LICENSE
Requires-Dist: cellxgene
Requires-Dist: flask
Requires-Dist: werkzeug
Requires-Dist: psutil
Requires-Dist: requests
